queuepipeio/__init__.py
queuepipeio-0.1.14.dist-info/licenses/LICENSE
queuepipeio-0.1.14.dist-info/METADATA
queuepipeio-0.1.14.dist-info/WHEEL
queuepipeio-0.1.14.dist-info/top_level.txt
queuepipeio-0.1.14.dist-info/RECORD
