Metadata-Version: 2.4
Name: queuepipeio
Version: 0.1.14
Summary: A pipe-based I/O library for efficient data transfer between threads with filtering support
Author-email: Your Name <your.email@example.com>
Maintainer-email: Your Name <your.email@example.com>
License-Expression: Apache-2.0
Project-URL: Homepage, https://github.com/yourusername/queuepipeio
Project-URL: Repository, https://github.com/yourusername/queuepipeio
Project-URL: Issues, https://github.com/yourusername/queuepipeio/issues
Classifier: Development Status :: 3 - Alpha
Classifier: Intended Audience :: Developers
Classifier: Programming Language :: Python :: 3
Classifier: Programming Language :: Python :: 3.8
Classifier: Programming Language :: Python :: 3.9
Classifier: Programming Language :: Python :: 3.10
Classifier: Programming Language :: Python :: 3.11
Classifier: Programming Language :: Python :: 3.12
Classifier: Operating System :: OS Independent
Requires-Python: >=3.8
License-File: LICENSE
Requires-Dist: tqdm
Provides-Extra: dev
Requires-Dist: boto3; extra == "dev"
Requires-Dist: black; extra == "dev"
Requires-Dist: flake8; extra == "dev"
Requires-Dist: bump2version; extra == "dev"
Requires-Dist: build; extra == "dev"
Requires-Dist: twine; extra == "dev"
Provides-Extra: test
Requires-Dist: boto3; extra == "test"
Dynamic: license-file
